py_glpi/__init__.py
py_glpi/connection.py
py_glpi/helpers.py
py_glpi/models.py
py_glpi/resources/__init__.py
py_glpi/resources/auth.py
py_glpi/resources/documents.py
py_glpi/resources/tickets.py
py_glpi-0.1.4.dist-info/licenses/LICENSE
py_glpi-0.1.4.dist-info/METADATA
py_glpi-0.1.4.dist-info/WHEEL
py_glpi-0.1.4.dist-info/top_level.txt
py_glpi-0.1.4.dist-info/RECORD
