Metadata-Version: 2.4
Name: py_glpi
Version: 0.1.4
Summary: A Python SDK for GLPI REST Api.
Author-email: Ricardo Marín <sidesrev@gmail.com>
License: MIT License
Classifier: Environment :: Web Environment
Classifier: Intended Audience :: Developers
Classifier: Operating System :: OS Independent
Classifier: License :: OSI Approved :: MIT License
Classifier: Programming Language :: Python
Classifier: Programming Language :: Python :: 3
Classifier: Programming Language :: Python :: 3 :: Only
Classifier: Programming Language :: Python :: 3.10
Requires-Python: >=3.10
License-File: LICENSE
Requires-Dist: arrow==1.3.0
Requires-Dist: build==1.2.2.post1
Requires-Dist: certifi==2024.12.14
Requires-Dist: charset-normalizer==3.4.1
Requires-Dist: exceptiongroup==1.2.2
Requires-Dist: idna==3.10
Requires-Dist: iniconfig==2.0.0
Requires-Dist: leopards==0.20.1
Requires-Dist: load-dotenv==0.1.0
Requires-Dist: packaging==24.2
Requires-Dist: pluggy==1.5.0
Requires-Dist: pyproject_hooks==1.2.0
Requires-Dist: python-dateutil==2.9.0.post0
Requires-Dist: python-dotenv==1.0.1
Requires-Dist: requests==2.32.3
Requires-Dist: six==1.17.0
Requires-Dist: tomli==2.2.1
Requires-Dist: types-python-dateutil==2.9.0.20241206
Requires-Dist: typing_extensions==4.12.2
Requires-Dist: urllib3==2.3.0
Provides-Extra: dev
Requires-Dist: pytest; extra == "dev"
Requires-Dist: pytest-cov; extra == "dev"
Dynamic: license-file
